poptoma/__init__.py
poptoma-0.0.1.dist-info/LICENSE
poptoma-0.0.1.dist-info/METADATA
poptoma-0.0.1.dist-info/WHEEL
poptoma-0.0.1.dist-info/top_level.txt
poptoma-0.0.1.dist-info/RECORD
