Metadata-Version: 2.1
Name: poptoma
Version: 0.0.1
Summary: A Python API for Optoma Projectors with web Admin
Home-page: https://github.com/wesleylima/poptoma
Author: Wesley Lima
Author-email: wesley@wesleylima.com
License: UNKNOWN
Platform: UNKNOWN
Classifier: Programming Language :: Python :: 3
Classifier: License :: OSI Approved :: GNU Affero General Public License v3 or later (AGPLv3+)
Classifier: Operating System :: OS Independent
Requires-Python: >=3.7
